morphic/__init__.py
morphic/autoenum.py
morphic/function.py
morphic/imports.py
morphic/registry.py
morphic/structs.py
morphic/typed.py
morphic-0.1.7.dist-info/METADATA
morphic-0.1.7.dist-info/WHEEL
morphic-0.1.7.dist-info/licenses/LICENSE
morphic-0.1.7.dist-info/RECORD
